odoo/addons/l10n_it_fatturapa_out_welfare/README.rst
odoo/addons/l10n_it_fatturapa_out_welfare/__init__.py
odoo/addons/l10n_it_fatturapa_out_welfare/__manifest__.py
odoo/addons/l10n_it_fatturapa_out_welfare/i18n/it.po
odoo/addons/l10n_it_fatturapa_out_welfare/i18n/l10n_it_fatturapa_out_welfare.pot
odoo/addons/l10n_it_fatturapa_out_welfare/models/__init__.py
odoo/addons/l10n_it_fatturapa_out_welfare/models/account_invoice.py
odoo/addons/l10n_it_fatturapa_out_welfare/models/account_invoice_line.py
odoo/addons/l10n_it_fatturapa_out_welfare/models/welfare_fund_type_amount.py
odoo/addons/l10n_it_fatturapa_out_welfare/readme/CONFIGURE.rst
odoo/addons/l10n_it_fatturapa_out_welfare/readme/DESCRIPTION.rst
odoo/addons/l10n_it_fatturapa_out_welfare/readme/USAGE.rst
odoo/addons/l10n_it_fatturapa_out_welfare/security/ir.model.access.csv
odoo/addons/l10n_it_fatturapa_out_welfare/static/description/icon.png
odoo/addons/l10n_it_fatturapa_out_welfare/static/description/index.html
odoo/addons/l10n_it_fatturapa_out_welfare/tests/__init__.py
odoo/addons/l10n_it_fatturapa_out_welfare/tests/test_fatturapa_out_welfare.py
odoo/addons/l10n_it_fatturapa_out_welfare/tests/data/IT06363391001_random.xml
odoo/addons/l10n_it_fatturapa_out_welfare/views/account_invoice_line_views.xml
odoo/addons/l10n_it_fatturapa_out_welfare/views/account_invoice_views.xml
odoo/addons/l10n_it_fatturapa_out_welfare/views/welfare_fund_type_amount_views.xml
odoo/addons/l10n_it_fatturapa_out_welfare/wizards/__init__.py
odoo/addons/l10n_it_fatturapa_out_welfare/wizards/wizard_export_fatturapa.py
odoo12_addon_l10n_it_fatturapa_out_welfare-12.0.1.0.2.dist-info/METADATA
odoo12_addon_l10n_it_fatturapa_out_welfare-12.0.1.0.2.dist-info/WHEEL
odoo12_addon_l10n_it_fatturapa_out_welfare-12.0.1.0.2.dist-info/top_level.txt
odoo12_addon_l10n_it_fatturapa_out_welfare-12.0.1.0.2.dist-info/RECORD
