Metadata-Version: 2.1
Name: odoo12-addon-l10n-it-fatturapa-out-welfare
Version: 12.0.1.0.2
Summary: Registrazione della cassa previdenziale nelle fatture elettroniche in uscita
Home-page: https://github.com/OCA/l10n-italy
Author: TAKOBI, Odoo Community Association (OCA)
Author-email: support@odoo-community.org
License: AGPL-3
Platform: UNKNOWN
Classifier: Programming Language :: Python
Classifier: Framework :: Odoo
Classifier: Framework :: Odoo :: 12.0
Classifier: License :: OSI Approved :: GNU Affero General Public License v3
Classifier: Development Status :: 4 - Beta
Requires-Python: >=3.5
Requires-Dist: odoo12-addon-l10n-it-fatturapa
Requires-Dist: odoo12-addon-l10n-it-fatturapa-out
Requires-Dist: odoo12-addon-l10n-it-fatturapa-out-wt
Requires-Dist: odoo <12.1dev,>=12.0a
